import_inspector/__init__.py
import_inspector/cli.py
import_inspector/cpu_profiler.py
import_inspector/detailed_profiler.py
import_inspector/memory_profiler.py
import_inspector-1.0.0.dist-info/METADATA
import_inspector-1.0.0.dist-info/WHEEL
import_inspector-1.0.0.dist-info/entry_points.txt
import_inspector-1.0.0.dist-info/top_level.txt
import_inspector-1.0.0.dist-info/RECORD
